mhy_api/__init__.py
mhy_api/bbs.py
mhy_api/geetest.py
mhy_api/genshin.py
mhy_api/test.py
mhy_api/tool.py
mhy_api-0.0.3.dist-info/METADATA
mhy_api-0.0.3.dist-info/WHEEL
mhy_api-0.0.3.dist-info/top_level.txt
mhy_api-0.0.3.dist-info/RECORD
